{"amountOfStarDust":11100,"amountOfGem":500,"whiteStarNum":3,"yellowStarNum":8,"blueStarNum":4,"normalStarGroupCreationLevel":9,"rareStarGroupCreationLevel":14,"epicStarGroupCreationLevel":8,"telescopeLevel":0,"playerLevel":0,"myCharactors":[{"name":"미닛","type":"rare","charactorID":13,"position":{"x":-2.0,"y":-3.215630292892456}}],"stargroups":[{"charactorID":13,"starGroup":[{"connections":[{"position":{"x":-1.073256015777588,"y":7.089787483215332},"starType":"yellow","index":1},{"position":{"x":-0.4998328685760498,"y":7.642870903015137},"starType":"yellow","index":2}]},{"connections":[{"position":{"x":-0.4998328685760498,"y":7.642870903015137},"starType":"yellow","index":2},{"position":{"x":0.793857991695404,"y":9.47032356262207},"starType":"yellow","index":0}]}]}],"currentDate":4}